tec/__init__.py
tec/backend.py
tec/client.py
tec/config.py
tec/main.py
tec/packer.py
tec/py.typed
the_everything_compiler-0.1.0.dist-info/licenses/LICENSE.TXT
the_everything_compiler-0.1.0.dist-info/METADATA
the_everything_compiler-0.1.0.dist-info/WHEEL
the_everything_compiler-0.1.0.dist-info/entry_points.txt
the_everything_compiler-0.1.0.dist-info/top_level.txt
the_everything_compiler-0.1.0.dist-info/RECORD
