Metadata-Version: 2.4
Name: the-everything-compiler
Version: 0.1.0
Summary: The Everything Compiler: Compiles anything you throw at it.
Author-email: Longhi <rafael@longhi.dev>
License-Expression: MIT
Project-URL: Homepage, https://github.com/longhirar/The-Everything-Compiler
Project-URL: Repository, https://github.com/longhirar/The-Everything-Compiler
Classifier: Development Status :: 3 - Alpha
Classifier: Intended Audience :: Developers
Classifier: Programming Language :: Python :: 3
Classifier: Topic :: Software Development :: Compilers
License-File: LICENSE.TXT
Requires-Dist: pathspec>=0.11.0
Requires-Dist: google-genai>=1.60.0
Requires-Dist: openai>=1.0.0
Requires-Dist: tomli>=2.0.0; python_version < "3.11"
Dynamic: license-file
